missing_mga/__init__.py
missing_mga/missing_methods.py
tests/__init__.py
tests/test_missing_methods.py
missing_mga-1.1.3.dist-info/LICENSE
missing_mga-1.1.3.dist-info/METADATA
missing_mga-1.1.3.dist-info/WHEEL
missing_mga-1.1.3.dist-info/top_level.txt
missing_mga-1.1.3.dist-info/RECORD
