Metadata-Version: 2.1
Name: missing_mga
Version: 1.1.3
Summary: A package for handling missing values in datasets.
Home-page: https://github.com/Mgobeaalcoba/missing_mga
Author: Mariano Gobea Alcoba
Author-email: gobeamariano@gmail.com
License: MIT
License-File: LICENSE
Requires-Dist: pandas
Requires-Dist: numpy
Requires-Dist: matplotlib
Requires-Dist: seaborn
Requires-Dist: upsetplot
Requires-Dist: scikit-learn
Requires-Dist: coverage
